sqeezz/__init__.py
sqeezz-0.1.0.dist-info/licenses/LICENSE
sqeezz-0.1.0.dist-info/WHEEL
sqeezz-0.1.0.dist-info/METADATA
sqeezz-0.1.0.dist-info/RECORD
