Metadata-Version: 2.4
Name: sqeezz
Version: 0.1.0
Summary: A lightweight dependency injection and service configuration library for Python
Keywords: dependency injection,service locator,configuration,async,testing
Author-email: Jeffrey Tackett <sqeezz@jeffreytackett.us>
Maintainer-email: Jeffrey Tackett <sqeezz@jeffreytackett.us>
Requires-Python: >=3.8
Classifier: Development Status :: 4 - Beta
Classifier: Intended Audience :: Developers
Classifier: License :: OSI Approved :: MIT License
Classifier: Operating System :: OS Independent
Classifier: Programming Language :: Python :: 3
Classifier: Programming Language :: Python :: 3.8
Classifier: Programming Language :: Python :: 3.9
Classifier: Programming Language :: Python :: 3.10
Classifier: Programming Language :: Python :: 3.11
Classifier: Programming Language :: Python :: 3.12
Classifier: Topic :: Software Development :: Libraries :: Python Modules
Classifier: Topic :: Utilities
License-File: LICENSE
Requires-Dist: pytest>=6.0 ; extra == "dev"
Requires-Dist: pytest-asyncio>=0.21.0 ; extra == "dev"
Requires-Dist: black>=22.0 ; extra == "dev"
Requires-Dist: flake8>=4.0 ; extra == "dev"
Requires-Dist: mypy>=0.910 ; extra == "dev"
Project-URL: Bug Tracker, https://github.com/jfftck/sqeezz/issues
Project-URL: Changelog, https://github.com/jfftck/sqeezz/blob/main/CHANGELOG.md
Project-URL: Documentation, https://github.com/jfftck/sqeezz#readme
Project-URL: Homepage, https://github.com/jfftck/sqeezz
Project-URL: Repository, https://github.com/jfftck/sqeezz
Provides-Extra: dev
